{"title":"[DarkX] Liza Rowe - Her 1st IR (20.05.2016)","uid":14666130,"size":459150604,"categoryP":"porn","categoryS":"movie_clips","magnet":"?xt=urn:btih:0b4db2379ae473e773cce4aa113c735b1a14cab0&amp;dn=+%5BDarkX%5D+Liza+Rowe+-+Her+1st+IR+%2820.05.2016%29+&amp;tr=udp%3A%2F%2Ftracker.leechers-paradise.org%3A6969&amp;tr=udp%3A%2F%2Fzer0day.ch%3A1337&amp;tr=udp%3A%2F%2Fopen.demonii.com%3A1337&amp;tr=udp%3A%2F%2Ftracker.coppersurfer.tk%3A6969&amp;tr=udp%3A%2F%2Fexodus.desync.com%3A6969","seeders":0,"leechers":1,"uploader":"LucasCar","files":1,"time":1463806016,"description":"[DarkX] Liza Rowe - Her 1st IR (20.05.2016) \r\n \nhttp://naughtyimage.com/img-573fcc1277e32.html\r\n\r\n\r\n\r\n★ ★ ★  For more Exclusive Porn please visit ★ ★ ★\r\n \nhttps://thepiratebay.org/user/LucasCar","torrent":{"xt":"urn:btih:0b4db2379ae473e773cce4aa113c735b1a14cab0","amp;dn":"+%5BDarkX%5D+Liza+Rowe+-+Her+1st+IR+%2820.05.2016%29+","amp;tr":["udp%3A%2F%2Ftracker.leechers-paradise.org%3A6969","udp%3A%2F%2Fzer0day.ch%3A1337","udp%3A%2F%2Fopen.demonii.com%3A1337","udp%3A%2F%2Ftracker.coppersurfer.tk%3A6969","udp%3A%2F%2Fexodus.desync.com%3A6969"],"infoHash":"0b4db2379ae473e773cce4aa113c735b1a14cab0","infoHashBuffer":{"type":"Buffer","data":[11,77,178,55,154,228,115,231,115,204,228,170,17,60,115,91,26,20,202,176]},"announce":[],"urlList":[]}}