{"title":"Charlotte Stokely and Lily Cade are in a lot of hot trouble","uid":15407795,"size":189976995,"categoryP":"porn","categoryS":"movie_clips","magnet":"?xt=urn:btih:186e157eb9c7bf4d5ba01c06df14897819fcc2e7&amp;dn=Charlotte+Stokely+and+Lily+Cade+are+in+a+lot+of+hot+trouble&amp;tr=udp%3A%2F%2Ftracker.leechers-paradise.org%3A6969&amp;tr=udp%3A%2F%2Fzer0day.ch%3A1337&amp;tr=udp%3A%2F%2Fopen.demonii.com%3A1337&amp;tr=udp%3A%2F%2Ftracker.coppersurfer.tk%3A6969&amp;tr=udp%3A%2F%2Fexodus.desync.com%3A6969","seeders":0,"leechers":3,"uploader":"luciano_x","files":1,"time":1469526042,"description":"SCREENSHOTS \nhttp://panustudio.site/viewer.php?file=31726410226245465875.jpg\r\n \nhttp://panustudio.site/viewer.php?file=42552909240261559155.jpg\r\n \nhttp://panustudio.site/viewer.php?file=31961042912089080695.jpg\r\n\r\n\r\n\r\nGet More Small Sized XXX Videos \nhttps://thepiratebay.org/user/luciano_x","torrent":{"xt":"urn:btih:186e157eb9c7bf4d5ba01c06df14897819fcc2e7","amp;dn":"Charlotte+Stokely+and+Lily+Cade+are+in+a+lot+of+hot+trouble","amp;tr":["udp%3A%2F%2Ftracker.leechers-paradise.org%3A6969","udp%3A%2F%2Fzer0day.ch%3A1337","udp%3A%2F%2Fopen.demonii.com%3A1337","udp%3A%2F%2Ftracker.coppersurfer.tk%3A6969","udp%3A%2F%2Fexodus.desync.com%3A6969"],"infoHash":"186e157eb9c7bf4d5ba01c06df14897819fcc2e7","infoHashBuffer":{"type":"Buffer","data":[24,110,21,126,185,199,191,77,91,160,28,6,223,20,137,120,25,252,194,231]},"announce":[],"urlList":[]}}