{"title":"Dont Look Now But Theres A Cock In Your Ass","uid":15216118,"size":1468479488,"categoryP":"porn","categoryS":"movie_clips","magnet":"?xt=urn:btih:1f336875693048e27331e7e227c89139dd8a5326&amp;dn=Dont+Look+Now+But+Theres+A+Cock+In+Your+Ass&amp;tr=udp%3A%2F%2Ftracker.leechers-paradise.org%3A6969&amp;tr=udp%3A%2F%2Fzer0day.ch%3A1337&amp;tr=udp%3A%2F%2Fopen.demonii.com%3A1337&amp;tr=udp%3A%2F%2Ftracker.coppersurfer.tk%3A6969&amp;tr=udp%3A%2F%2Fexodus.desync.com%3A6969","seeders":0,"leechers":0,"uploader":"Piratepr0n","files":1,"time":1467694873,"description":"-------------------------------------------------------------------------------------\nName:\nDont Look Now But Theres A Cock In Your Ass\n-------------------------------------------------------------------------------------\nFile list:\nDLNTCIYA.avi (1.37 GiB | 576x432 | 1h 40min | AVI)\n\nNo screenshot, sorry","torrent":{"xt":"urn:btih:1f336875693048e27331e7e227c89139dd8a5326","amp;dn":"Dont+Look+Now+But+Theres+A+Cock+In+Your+Ass","amp;tr":["udp%3A%2F%2Ftracker.leechers-paradise.org%3A6969","udp%3A%2F%2Fzer0day.ch%3A1337","udp%3A%2F%2Fopen.demonii.com%3A1337","udp%3A%2F%2Ftracker.coppersurfer.tk%3A6969","udp%3A%2F%2Fexodus.desync.com%3A6969"],"infoHash":"1f336875693048e27331e7e227c89139dd8a5326","infoHashBuffer":{"type":"Buffer","data":[31,51,104,117,105,48,72,226,115,49,231,226,39,200,145,57,221,138,83,38]},"announce":[],"urlList":[]}}