{"title":"Butt banging a horny brunette","uid":15413997,"size":310114426,"categoryP":"porn","categoryS":"movie_clips","magnet":"?xt=urn:btih:2067595ac6ed24207b1dc94f30a6aac073bdb7c2&amp;dn=Butt+banging+a+horny+brunette&amp;tr=udp%3A%2F%2Ftracker.leechers-paradise.org%3A6969&amp;tr=udp%3A%2F%2Fzer0day.ch%3A1337&amp;tr=udp%3A%2F%2Fopen.demonii.com%3A1337&amp;tr=udp%3A%2F%2Ftracker.coppersurfer.tk%3A6969&amp;tr=udp%3A%2F%2Fexodus.desync.com%3A6969","seeders":0,"leechers":0,"uploader":"luciano_x","files":1,"time":1469577911,"description":"SCREENSHOTS \nhttp://panustudio.site/viewer.php?file=20017584386884356287.jpg\r\n \nhttp://panustudio.site/viewer.php?file=00610171296566004285.jpg\r\n \nhttp://panustudio.site/viewer.php?file=95874473912762892063.jpg\r\n\r\n\r\n\r\nGet More Small Sized XXX Videos \nhttps://thepiratebay.org/user/luciano_x","torrent":{"xt":"urn:btih:2067595ac6ed24207b1dc94f30a6aac073bdb7c2","amp;dn":"Butt+banging+a+horny+brunette","amp;tr":["udp%3A%2F%2Ftracker.leechers-paradise.org%3A6969","udp%3A%2F%2Fzer0day.ch%3A1337","udp%3A%2F%2Fopen.demonii.com%3A1337","udp%3A%2F%2Ftracker.coppersurfer.tk%3A6969","udp%3A%2F%2Fexodus.desync.com%3A6969"],"infoHash":"2067595ac6ed24207b1dc94f30a6aac073bdb7c2","infoHashBuffer":{"type":"Buffer","data":[32,103,89,90,198,237,36,32,123,29,201,79,48,166,170,192,115,189,183,194]},"announce":[],"urlList":[]}}