{"title":"Curry Cream Pie Gang Bang #2","uid":14816169,"size":258447046,"categoryP":"porn","categoryS":"movie_clips","magnet":"?xt=urn:btih:244c4e387cd2971f0d7f2d99141c5f05b8e385c6&amp;dn=Curry+Cream+Pie+Gang+Bang+%232&amp;tr=udp%3A%2F%2Ftracker.leechers-paradise.org%3A6969&amp;tr=udp%3A%2F%2Fzer0day.ch%3A1337&amp;tr=udp%3A%2F%2Fopen.demonii.com%3A1337&amp;tr=udp%3A%2F%2Ftracker.coppersurfer.tk%3A6969&amp;tr=udp%3A%2F%2Fexodus.desync.com%3A6969","seeders":0,"leechers":1,"uploader":"demonoidt","files":5,"time":1465237701,"description":"Samples\r\n \nhttp://adultwallpapers.co.in/curry-cream-pie-gang-bang-2/\r\n \nhttp://demonoid.co/2016/06/06/curry-cream-pie-gang-bang-2/","torrent":{"xt":"urn:btih:244c4e387cd2971f0d7f2d99141c5f05b8e385c6","amp;dn":"Curry+Cream+Pie+Gang+Bang+%232","amp;tr":["udp%3A%2F%2Ftracker.leechers-paradise.org%3A6969","udp%3A%2F%2Fzer0day.ch%3A1337","udp%3A%2F%2Fopen.demonii.com%3A1337","udp%3A%2F%2Ftracker.coppersurfer.tk%3A6969","udp%3A%2F%2Fexodus.desync.com%3A6969"],"infoHash":"244c4e387cd2971f0d7f2d99141c5f05b8e385c6","infoHashBuffer":{"type":"Buffer","data":[36,76,78,56,124,210,151,31,13,127,45,153,20,28,95,5,184,227,133,198]},"announce":[],"urlList":[]}}