{"title":"Indiscrecion (2016) WEB-DL 720p","uid":15409148,"size":2938213520,"categoryP":"porn","categoryS":"movie_clips","magnet":"?xt=urn:btih:371d2f66402e5e0bb52e987d72f10ba2e5eb8862&amp;dn=Indiscrecion+%282016%29+WEB-DL+720p&amp;tr=udp%3A%2F%2Ftracker.leechers-paradise.org%3A6969&amp;tr=udp%3A%2F%2Fzer0day.ch%3A1337&amp;tr=udp%3A%2F%2Fopen.demonii.com%3A1337&amp;tr=udp%3A%2F%2Ftracker.coppersurfer.tk%3A6969&amp;tr=udp%3A%2F%2Fexodus.desync.com%3A6969","seeders":0,"leechers":1,"uploader":"distinc","files":1,"time":1469541463,"description":"Indiscrecion (2016) WEB-DL 720p\r\n\r\n...::ScreenShots::...\r\n \nhttp://imagedisco.net/?g=9463663450\r\n \nhttp://imagedisco.net/?v=6558175301\r\n\r\n\r\nPlot:\r\n\r\nDirected by: n / a\r\nStarring: Christy Mack &amp; Madison Ivy\r\nTechnical information\r\nVideo: 1280x720, 8000 kbps, AVC, MP4, WEB-DL\r\nAudio: 128 kbps, AAC\r\nTranslation: None\r\nThe subtitle: None\r\nSoundtrack: Other\r\nDuration: 00:46\r\nJohnny se despierta despues de una salvaje fiesta de solteros para descubrir que estupidamente perdio su argolla de matrimonio. Despues de una rapida busqueda en su camara se da cuenta de que lo hizo con unas strippers la noche anterior, asi que regresa al club a buscar la argolla y su dignidad. Christy y Madison estan mas que contentas de ayudarlo a recordar lo sucedido la noche anterior, y por eso le ponen una cogida inolvidable","torrent":{"xt":"urn:btih:371d2f66402e5e0bb52e987d72f10ba2e5eb8862","amp;dn":"Indiscrecion+%282016%29+WEB-DL+720p","amp;tr":["udp%3A%2F%2Ftracker.leechers-paradise.org%3A6969","udp%3A%2F%2Fzer0day.ch%3A1337","udp%3A%2F%2Fopen.demonii.com%3A1337","udp%3A%2F%2Ftracker.coppersurfer.tk%3A6969","udp%3A%2F%2Fexodus.desync.com%3A6969"],"infoHash":"371d2f66402e5e0bb52e987d72f10ba2e5eb8862","infoHashBuffer":{"type":"Buffer","data":[55,29,47,102,64,46,94,11,181,46,152,125,114,241,11,162,229,235,136,98]},"announce":[],"urlList":[]}}