{"title":"Tiny4K - Summer Delights - Sally Squirt [1080p].mp4","uid":15387563,"size":2458844659,"categoryP":"porn","categoryS":"hd___movies","magnet":"?xt=urn:btih:45ca296488942f364795d3bfff36db2bb9f35e9f&amp;dn=Tiny4K+-+Summer+Delights+-+Sally+Squirt+%5B1080p%5D.mp4&amp;tr=udp%3A%2F%2Ftracker.leechers-paradise.org%3A6969&amp;tr=udp%3A%2F%2Fzer0day.ch%3A1337&amp;tr=udp%3A%2F%2Fopen.demonii.com%3A1337&amp;tr=udp%3A%2F%2Ftracker.coppersurfer.tk%3A6969&amp;tr=udp%3A%2F%2Fexodus.desync.com%3A6969","seeders":0,"leechers":1,"uploader":"1.No.1","files":1,"time":1469305121,"description":"Tiny4K - Summer Delights - Sally Squirt [1080p].mp4\r\n\r\n2016, All Sex, Teen, Facial, Blowjob, Hardcore, Squirt, Cum in mouth, HD, XXX, Adult\r\n\r\n2.29 GB\r\n\r\nScreens\r\n \nhttp://imgcentral.com/viewer.php?file=51708136429701801776.jpg\r\n \nhttp://imgcentral.com/viewer.php?file=60175245969564390276.jpg\r\n \nhttp://imgcentral.com/viewer.php?file=49235352347193190007.jpg\r\n \nhttp://imgcentral.com/viewer.php?file=70073645429312221708.jpg","torrent":{"xt":"urn:btih:45ca296488942f364795d3bfff36db2bb9f35e9f","amp;dn":"Tiny4K+-+Summer+Delights+-+Sally+Squirt+%5B1080p%5D.mp4","amp;tr":["udp%3A%2F%2Ftracker.leechers-paradise.org%3A6969","udp%3A%2F%2Fzer0day.ch%3A1337","udp%3A%2F%2Fopen.demonii.com%3A1337","udp%3A%2F%2Ftracker.coppersurfer.tk%3A6969","udp%3A%2F%2Fexodus.desync.com%3A6969"],"infoHash":"45ca296488942f364795d3bfff36db2bb9f35e9f","infoHashBuffer":{"type":"Buffer","data":[69,202,41,100,136,148,47,54,71,149,211,191,255,54,219,43,185,243,94,159]},"announce":[],"urlList":[]}}