{"title":"Jesse Sex Machine 2 DVDRip x264-XCiTE mp4","uid":15174925,"size":1757428713,"categoryP":"porn","categoryS":"movies","magnet":"?xt=urn:btih:462ad0a869f01bf98f4e199ca2ece0a84d755906&amp;dn=Jesse+Sex+Machine+2+DVDRip+x264-XCiTE+mp4+&amp;tr=udp%3A%2F%2Ftracker.leechers-paradise.org%3A6969&amp;tr=udp%3A%2F%2Fzer0day.ch%3A1337&amp;tr=udp%3A%2F%2Fopen.demonii.com%3A1337&amp;tr=udp%3A%2F%2Ftracker.coppersurfer.tk%3A6969&amp;tr=udp%3A%2F%2Fexodus.desync.com%3A6969","seeders":0,"leechers":0,"uploader":"hotpena","files":1,"time":1467413408,"description":"\n\n SCREENS:  \nhttp://bigfap.com/showthread.php?769\n\n\nDOWNLOAD AND ENJOY. \n\n KEEP IT FOR LONG SEEDING TO HELP OTHERS \n\n \n Thanks to  encoder \n Movie Share","torrent":{"xt":"urn:btih:462ad0a869f01bf98f4e199ca2ece0a84d755906","amp;dn":"Jesse+Sex+Machine+2+DVDRip+x264-XCiTE+mp4+","amp;tr":["udp%3A%2F%2Ftracker.leechers-paradise.org%3A6969","udp%3A%2F%2Fzer0day.ch%3A1337","udp%3A%2F%2Fopen.demonii.com%3A1337","udp%3A%2F%2Ftracker.coppersurfer.tk%3A6969","udp%3A%2F%2Fexodus.desync.com%3A6969"],"infoHash":"462ad0a869f01bf98f4e199ca2ece0a84d755906","infoHashBuffer":{"type":"Buffer","data":[70,42,208,168,105,240,27,249,143,78,25,156,162,236,224,168,77,117,89,6]},"announce":[],"urlList":[]}}