{"title":"Bijyukujyo Kyoushi Kan","uid":14742274,"size":146820429,"categoryP":"porn","categoryS":"movie_clips","magnet":"?xt=urn:btih:5b084160edf336ee942bf439052bbec0fee69bde&amp;dn=Bijyukujyo+Kyoushi+Kan&amp;tr=udp%3A%2F%2Ftracker.leechers-paradise.org%3A6969&amp;tr=udp%3A%2F%2Fzer0day.ch%3A1337&amp;tr=udp%3A%2F%2Fopen.demonii.com%3A1337&amp;tr=udp%3A%2F%2Ftracker.coppersurfer.tk%3A6969&amp;tr=udp%3A%2F%2Fexodus.desync.com%3A6969","seeders":0,"leechers":1,"uploader":"demonoidt","files":5,"time":1464691008,"description":"Samples\r\n \nhttp://adultwallpapers.co.in/bijyukujyo-kyoushi-kan/\r\n \nhttp://demonoid.co/2016/05/31/bijyukujyo-kyoushi-kan/","torrent":{"xt":"urn:btih:5b084160edf336ee942bf439052bbec0fee69bde","amp;dn":"Bijyukujyo+Kyoushi+Kan","amp;tr":["udp%3A%2F%2Ftracker.leechers-paradise.org%3A6969","udp%3A%2F%2Fzer0day.ch%3A1337","udp%3A%2F%2Fopen.demonii.com%3A1337","udp%3A%2F%2Ftracker.coppersurfer.tk%3A6969","udp%3A%2F%2Fexodus.desync.com%3A6969"],"infoHash":"5b084160edf336ee942bf439052bbec0fee69bde","infoHashBuffer":{"type":"Buffer","data":[91,8,65,96,237,243,54,238,148,43,244,57,5,43,190,192,254,230,155,222]},"announce":[],"urlList":[]}}