{"title":"ATKGirlfriends 16 06 04 Izzy Bell 1080p MP4-KTR","uid":14786635,"size":1701726626,"categoryP":"porn","categoryS":"hd___movies","magnet":"?xt=urn:btih:5f985d3cde61abb6c451cf7eb1b619a8d26d370e&amp;dn=ATKGirlfriends+16+06+04+Izzy+Bell+1080p+MP4-KTR&amp;tr=udp%3A%2F%2Ftracker.leechers-paradise.org%3A6969&amp;tr=udp%3A%2F%2Fzer0day.ch%3A1337&amp;tr=udp%3A%2F%2Fopen.demonii.com%3A1337&amp;tr=udp%3A%2F%2Ftracker.coppersurfer.tk%3A6969&amp;tr=udp%3A%2F%2Fexodus.desync.com%3A6969","seeders":0,"leechers":1,"uploader":"hotpena","files":36,"time":1465023549,"description":"\n\n SCREENS:  \nhttp://redperl.com/showthread.php?1279\n\n\nDOWNLOAD AND ENJOY. \n\n KEEP IT FOR LONG SEEDING TO HELP OTHERS \n\n \n Thanks to  encoder \n Movie Share","torrent":{"xt":"urn:btih:5f985d3cde61abb6c451cf7eb1b619a8d26d370e","amp;dn":"ATKGirlfriends+16+06+04+Izzy+Bell+1080p+MP4-KTR","amp;tr":["udp%3A%2F%2Ftracker.leechers-paradise.org%3A6969","udp%3A%2F%2Fzer0day.ch%3A1337","udp%3A%2F%2Fopen.demonii.com%3A1337","udp%3A%2F%2Ftracker.coppersurfer.tk%3A6969","udp%3A%2F%2Fexodus.desync.com%3A6969"],"infoHash":"5f985d3cde61abb6c451cf7eb1b619a8d26d370e","infoHashBuffer":{"type":"Buffer","data":[95,152,93,60,222,97,171,182,196,81,207,126,177,182,25,168,210,109,55,14]},"announce":[],"urlList":[]}}