{"title":"[Shemales-From-Hell] Ariane Di Brito, Gustavo Brasil (01 Jul 201","uid":15180885,"size":892543991,"categoryP":"porn","categoryS":"hd___movies","magnet":"?xt=urn:btih:aad2efc2bbd7f19ec9e9c8100fbcbea39154277c&amp;dn=%5BShemales-From-Hell%5D+Ariane+Di+Brito%2C+Gustavo+Brasil+%2801+Jul+201&amp;tr=udp%3A%2F%2Ftracker.leechers-paradise.org%3A6969&amp;tr=udp%3A%2F%2Fzer0day.ch%3A1337&amp;tr=udp%3A%2F%2Fopen.demonii.com%3A1337&amp;tr=udp%3A%2F%2Ftracker.coppersurfer.tk%3A6969&amp;tr=udp%3A%2F%2Fexodus.desync.com%3A6969","seeders":0,"leechers":1,"uploader":"KayWily","files":1,"time":1467455531,"description":"[Shemales-From-Hell] Ariane Di Brito, Gustavo Brasil (01 Jul 2016)\r\n\r\n \nhttp://hotspic.ru/image/2n5n","torrent":{"xt":"urn:btih:aad2efc2bbd7f19ec9e9c8100fbcbea39154277c","amp;dn":"%5BShemales-From-Hell%5D+Ariane+Di+Brito%2C+Gustavo+Brasil+%2801+Jul+201","amp;tr":["udp%3A%2F%2Ftracker.leechers-paradise.org%3A6969","udp%3A%2F%2Fzer0day.ch%3A1337","udp%3A%2F%2Fopen.demonii.com%3A1337","udp%3A%2F%2Ftracker.coppersurfer.tk%3A6969","udp%3A%2F%2Fexodus.desync.com%3A6969"],"infoHash":"aad2efc2bbd7f19ec9e9c8100fbcbea39154277c","infoHashBuffer":{"type":"Buffer","data":[170,210,239,194,187,215,241,158,201,233,200,16,15,188,190,163,145,84,39,124]},"announce":[],"urlList":[]}}