{"title":"TeenyPlayground E24 Veronika XXX 1080p MP4","uid":14843003,"size":1052833765,"categoryP":"porn","categoryS":"hd___movies","magnet":"?xt=urn:btih:acf854498a4ec8d481cf655ff9bcadf3fb6e8792&amp;dn=TeenyPlayground+E24+Veronika+XXX+1080p+MP4&amp;tr=udp%3A%2F%2Ftracker.leechers-paradise.org%3A6969&amp;tr=udp%3A%2F%2Fzer0day.ch%3A1337&amp;tr=udp%3A%2F%2Fopen.demonii.com%3A1337&amp;tr=udp%3A%2F%2Ftracker.coppersurfer.tk%3A6969&amp;tr=udp%3A%2F%2Fexodus.desync.com%3A6969","seeders":0,"leechers":0,"uploader":"RandalPaul","files":1,"time":1465395550,"description":"\n Media INFO &amp; Screenshots \n \n  Duration \t:  17min 13s \n  Size \t\t:  1 004 MiB \n  WidthxHeight \t:  1920x1080  \n  Video Format \t:  MPEG-4  \n\n  Image Links \t:  http://imgshag.com/image/UxqV9  \n\n  Image Sheet \t:  http://imgshag.com/image/Ux9PI \n\n \t \t \t Get More Small Sized XXX Videos \n \n \t   https://thepiratebay.se/user/RandalPaul/","torrent":{"xt":"urn:btih:acf854498a4ec8d481cf655ff9bcadf3fb6e8792","amp;dn":"TeenyPlayground+E24+Veronika+XXX+1080p+MP4","amp;tr":["udp%3A%2F%2Ftracker.leechers-paradise.org%3A6969","udp%3A%2F%2Fzer0day.ch%3A1337","udp%3A%2F%2Fopen.demonii.com%3A1337","udp%3A%2F%2Ftracker.coppersurfer.tk%3A6969","udp%3A%2F%2Fexodus.desync.com%3A6969"],"infoHash":"acf854498a4ec8d481cf655ff9bcadf3fb6e8792","infoHashBuffer":{"type":"Buffer","data":[172,248,84,73,138,78,200,212,129,207,101,95,249,188,173,243,251,110,135,146]},"announce":[],"urlList":[]}}