{"title":"Casted cumshot trio with euro babes","uid":15185678,"size":182109756,"categoryP":"porn","categoryS":"movie_clips","magnet":"?xt=urn:btih:cbfb19b1a9dbad8f917d248f0ad6cf0acaedd90c&amp;dn=Casted+cumshot+trio+with+euro+babes&amp;tr=udp%3A%2F%2Ftracker.leechers-paradise.org%3A6969&amp;tr=udp%3A%2F%2Fzer0day.ch%3A1337&amp;tr=udp%3A%2F%2Fopen.demonii.com%3A1337&amp;tr=udp%3A%2F%2Ftracker.coppersurfer.tk%3A6969&amp;tr=udp%3A%2F%2Fexodus.desync.com%3A6969","seeders":0,"leechers":1,"uploader":"luciano_x","files":1,"time":1467492037,"description":"SCREENSHOTS \nhttp://panustudio.site/image/Cso\r\n \nhttp://panustudio.site/image/Cs5\r\n \nhttp://panustudio.site/image/Cs6\r\n\r\nMY TORRENTS \nhttps://thepiratebay.org/user/luciano_x","torrent":{"xt":"urn:btih:cbfb19b1a9dbad8f917d248f0ad6cf0acaedd90c","amp;dn":"Casted+cumshot+trio+with+euro+babes","amp;tr":["udp%3A%2F%2Ftracker.leechers-paradise.org%3A6969","udp%3A%2F%2Fzer0day.ch%3A1337","udp%3A%2F%2Fopen.demonii.com%3A1337","udp%3A%2F%2Ftracker.coppersurfer.tk%3A6969","udp%3A%2F%2Fexodus.desync.com%3A6969"],"infoHash":"cbfb19b1a9dbad8f917d248f0ad6cf0acaedd90c","infoHashBuffer":{"type":"Buffer","data":[203,251,25,177,169,219,173,143,145,125,36,143,10,214,207,10,202,237,217,12]},"announce":[],"urlList":[]}}