{"title":"Flirt XXX DVDRip [.avi]","uid":14887007,"size":902332416,"categoryP":"porn","categoryS":"movies","magnet":"?xt=urn:btih:d21677277f84767d9f3df41620d8083ea8051f4a&amp;dn=Flirt+XXX+DVDRip+%5B.avi%5D&amp;tr=udp%3A%2F%2Ftracker.leechers-paradise.org%3A6969&amp;tr=udp%3A%2F%2Fzer0day.ch%3A1337&amp;tr=udp%3A%2F%2Fopen.demonii.com%3A1337&amp;tr=udp%3A%2F%2Ftracker.coppersurfer.tk%3A6969&amp;tr=udp%3A%2F%2Fexodus.desync.com%3A6969","seeders":0,"leechers":1,"uploader":"C47wh15p3r3r","files":1,"time":1465742258,"description":"Flirt XXX DVDRip [.avi]\r\n\r\nScreenshots: \nhttp://www.imglocate.com/?v=214906 \nhttp://www.imglocate.com/?v=449788","torrent":{"xt":"urn:btih:d21677277f84767d9f3df41620d8083ea8051f4a","amp;dn":"Flirt+XXX+DVDRip+%5B.avi%5D","amp;tr":["udp%3A%2F%2Ftracker.leechers-paradise.org%3A6969","udp%3A%2F%2Fzer0day.ch%3A1337","udp%3A%2F%2Fopen.demonii.com%3A1337","udp%3A%2F%2Ftracker.coppersurfer.tk%3A6969","udp%3A%2F%2Fexodus.desync.com%3A6969"],"infoHash":"d21677277f84767d9f3df41620d8083ea8051f4a","infoHashBuffer":{"type":"Buffer","data":[210,22,119,39,127,132,118,125,159,61,244,22,32,216,8,62,168,5,31,74]},"announce":[],"urlList":[]}}