{"title":"09 - Music","uid":15182295,"size":384015173,"categoryP":"porn","categoryS":"movie_clips","magnet":"?xt=urn:btih:d5e185937d6a02f395750c06f51905f810f6def3&amp;dn=09+-+Music&amp;tr=udp%3A%2F%2Ftracker.leechers-paradise.org%3A6969&amp;tr=udp%3A%2F%2Fzer0day.ch%3A1337&amp;tr=udp%3A%2F%2Fopen.demonii.com%3A1337&amp;tr=udp%3A%2F%2Ftracker.coppersurfer.tk%3A6969&amp;tr=udp%3A%2F%2Fexodus.desync.com%3A6969","seeders":0,"leechers":0,"uploader":"Piratepr0n","files":12,"time":1467466336,"description":"-------------------------------------------------------------------------------------\nName:\n09 - Music\n-------------------------------------------------------------------------------------\nFile list:\n#1539 - DHV Sissy Radar.flv (16.0 MiB | 582x388 | 4min 27s | Flash Video) \nhttp://imgfapper.com/img-5777a641417c7.html \n\n#1566 – Submissive Desire.mp4 (36.6 MiB | 720x480 | 7min 2s | MPEG-4) \nhttp://imgfapper.com/img-5777a644ac349.html \n\n#1669 - DHV Hey Baby.flv (25.8 MiB | 582x388 | 7min 7s | Flash Video) \nhttp://imgfapper.com/img-5777a646edb15.html \n\n#2875 – Shemale Music Video Vol. 1.mp4 (13.6 MiB | 852x480 | 2min 33s | MPEG-4) \nhttp://imgfapper.com/img-5777a6494c61b.html \n\nChampions Of Cocknia - Sissy Sandra.mp4 (180 MiB | 864x480 | 35min 35s | MPEG-4) \nhttp://imgfapper.com/img-5777a64b95874.html \n\nFeminized Sissy Lust.flv (12.2 MiB | 646x364 | 3min 23s | Flash Video) \nhttp://imgfapper.com/img-5777a64dde801.html \n\nGynodrome Sissy Life #2 (no words) .flv (11.8 MiB | 646x364 | 3min 17s | Flash Video) \nhttp://imgfapper.com/img-5777a65032a9a.html \n\nHIS#5 Monster Cocks.flv (18.0 MiB | 646x364 | 4min 59s | Flash Video) \nhttp://imgfapper.com/img-5777a6526e3c8.html \n\nIm Wide Awake.flv (13.6 MiB | 646x364 | 3min 51s | Flash Video) \nhttp://imgfapper.com/img-5777a654b6cbd.html \n\nSissy Couture 1645 DHV Quicky.flv (2.79 MiB | 542x406 | 46s 194ms | Flash Video) \nhttp://imgfapper.com/img-5777a65715706.html \n\nStraight to the point.flv (22.5 MiB | 644x364 | 6min 15s | Flash Video) \nhttp://imgfapper.com/img-5777a659603d1.html \n\nWould you.. 1080P.flv (12.8 MiB | 646x364 | 3min 30s | Flash Video) \nhttp://imgfapper.com/img-5777a65ba4824.html","torrent":{"xt":"urn:btih:d5e185937d6a02f395750c06f51905f810f6def3","amp;dn":"09+-+Music","amp;tr":["udp%3A%2F%2Ftracker.leechers-paradise.org%3A6969","udp%3A%2F%2Fzer0day.ch%3A1337","udp%3A%2F%2Fopen.demonii.com%3A1337","udp%3A%2F%2Ftracker.coppersurfer.tk%3A6969","udp%3A%2F%2Fexodus.desync.com%3A6969"],"infoHash":"d5e185937d6a02f395750c06f51905f810f6def3","infoHashBuffer":{"type":"Buffer","data":[213,225,133,147,125,106,2,243,149,117,12,6,245,25,5,248,16,246,222,243]},"announce":[],"urlList":[]}}