{"title":"[Hegre-Art] 2009-12-01 - Thea - Soothing Body Massage [MP4][1440","uid":14815620,"size":1969476957,"categoryP":"porn","categoryS":"hd___movies","magnet":"?xt=urn:btih:e00314e5a365dd76a245009cbe21733643424a8f&amp;dn=%5BHegre-Art%5D+2009-12-01+-+Thea+-+Soothing+Body+Massage+%5BMP4%5D%5B1440&amp;tr=udp%3A%2F%2Ftracker.leechers-paradise.org%3A6969&amp;tr=udp%3A%2F%2Fzer0day.ch%3A1337&amp;tr=udp%3A%2F%2Fopen.demonii.com%3A1337&amp;tr=udp%3A%2F%2Ftracker.coppersurfer.tk%3A6969&amp;tr=udp%3A%2F%2Fexodus.desync.com%3A6969","seeders":0,"leechers":1,"uploader":"Piratepr0n","files":1,"time":1465234764,"description":"-------------------------------------------------------------------------------------\nName:\n[Hegre-Art] 2009-12-01 - Thea - Soothing Body Massage [MP4][1440x1080]\n-------------------------------------------------------------------------------------\nFile list:\n[Hegre-Art] 2009-12-01 - Thea - Soothing Body Massage [MP4][1440x1080].mp4 (1.83 GiB | 1440x1080 | 54min 1s | MPEG-4) \nhttp://imgfapper.com/img-5755992477806.html","torrent":{"xt":"urn:btih:e00314e5a365dd76a245009cbe21733643424a8f","amp;dn":"%5BHegre-Art%5D+2009-12-01+-+Thea+-+Soothing+Body+Massage+%5BMP4%5D%5B1440","amp;tr":["udp%3A%2F%2Ftracker.leechers-paradise.org%3A6969","udp%3A%2F%2Fzer0day.ch%3A1337","udp%3A%2F%2Fopen.demonii.com%3A1337","udp%3A%2F%2Ftracker.coppersurfer.tk%3A6969","udp%3A%2F%2Fexodus.desync.com%3A6969"],"infoHash":"e00314e5a365dd76a245009cbe21733643424a8f","infoHashBuffer":{"type":"Buffer","data":[224,3,20,229,163,101,221,118,162,69,0,156,190,33,115,54,67,66,74,143]},"announce":[],"urlList":[]}}