{"title":"[FemaleFakeTaxi] Michelle Thorne Stud Cums In Busty Blondes Mout","uid":15493199,"size":1544852879,"categoryP":"porn","categoryS":"other","magnet":"?xt=urn:btih:e780d09fdd61950be393d82f239aafa22642c76c&amp;dn=%5BFemaleFakeTaxi%5D+Michelle+Thorne+Stud+Cums+In+Busty+Blondes+Mout&amp;tr=udp%3A%2F%2Ftracker.leechers-paradise.org%3A6969&amp;tr=udp%3A%2F%2Fzer0day.ch%3A1337&amp;tr=udp%3A%2F%2Fopen.demonii.com%3A1337&amp;tr=udp%3A%2F%2Ftracker.coppersurfer.tk%3A6969&amp;tr=udp%3A%2F%2Fexodus.desync.com%3A6969","seeders":0,"leechers":1,"uploader":"jimko9034","files":3,"time":1470397217,"description":"Screenshots:\r\n\r\n\r\n \nhttp://imghorse.com/img3/y5o669l0eg/\r\n\r\n \nhttp://imghorse.com/img3/j2jhdqdm5n/\r\n\r\n \nhttp://imghorse.com/img3/hfgdg27st3/\r\n\r\n\r\n\r\n[FemaleFakeTaxi] Michelle Thorne Stud Cums In Busty Blondes Mouth","torrent":{"xt":"urn:btih:e780d09fdd61950be393d82f239aafa22642c76c","amp;dn":"%5BFemaleFakeTaxi%5D+Michelle+Thorne+Stud+Cums+In+Busty+Blondes+Mout","amp;tr":["udp%3A%2F%2Ftracker.leechers-paradise.org%3A6969","udp%3A%2F%2Fzer0day.ch%3A1337","udp%3A%2F%2Fopen.demonii.com%3A1337","udp%3A%2F%2Ftracker.coppersurfer.tk%3A6969","udp%3A%2F%2Fexodus.desync.com%3A6969"],"infoHash":"e780d09fdd61950be393d82f239aafa22642c76c","infoHashBuffer":{"type":"Buffer","data":[231,128,208,159,221,97,149,11,227,147,216,47,35,154,175,162,38,66,199,108]},"announce":[],"urlList":[]}}