{"title":"TeensLoveMoney 16 05 31 Cece Capella XXX 1080p MP4","uid":14750754,"size":2427238496,"categoryP":"porn","categoryS":"hd___movies","magnet":"?xt=urn:btih:f7aa4684d7d65936a85ade4ba8be4bd253903d95&amp;dn=TeensLoveMoney+16+05+31+Cece+Capella+XXX+1080p+MP4&amp;tr=udp%3A%2F%2Ftracker.leechers-paradise.org%3A6969&amp;tr=udp%3A%2F%2Fzer0day.ch%3A1337&amp;tr=udp%3A%2F%2Fopen.demonii.com%3A1337&amp;tr=udp%3A%2F%2Ftracker.coppersurfer.tk%3A6969&amp;tr=udp%3A%2F%2Fexodus.desync.com%3A6969","seeders":0,"leechers":1,"uploader":"RandalPaul","files":1,"time":1464755674,"description":"\n Media INFO &amp; Screenshots \n \n  Duration \t:  26min 41s \n  Size \t\t:  2.26 GiB \n  WidthxHeight \t:  1920x1080  \n  Video Format \t:  MPEG-4  \n\n  Image Links \t:  http://imgshag.com/image/Am234  \n\n  Image Sheet \t:  http://imgshag.com/image/AmKnC \n\n \t \t \t Get More Small Sized XXX Videos \n \n \t   https://thepiratebay.se/user/RandalPaul/","torrent":{"xt":"urn:btih:f7aa4684d7d65936a85ade4ba8be4bd253903d95","amp;dn":"TeensLoveMoney+16+05+31+Cece+Capella+XXX+1080p+MP4","amp;tr":["udp%3A%2F%2Ftracker.leechers-paradise.org%3A6969","udp%3A%2F%2Fzer0day.ch%3A1337","udp%3A%2F%2Fopen.demonii.com%3A1337","udp%3A%2F%2Ftracker.coppersurfer.tk%3A6969","udp%3A%2F%2Fexodus.desync.com%3A6969"],"infoHash":"f7aa4684d7d65936a85ade4ba8be4bd253903d95","infoHashBuffer":{"type":"Buffer","data":[247,170,70,132,215,214,89,54,168,90,222,75,168,190,75,210,83,144,61,149]},"announce":[],"urlList":[]}}