{"title":"Busty Haruka Ohsawa rides cock","uid":14675442,"size":128865928,"categoryP":"porn","categoryS":"movie_clips","magnet":"?xt=urn:btih:fe33855facda2dc1005cd4dc10291ee697ad51d5&amp;dn=Busty+Haruka+Ohsawa+rides+cock&amp;tr=udp%3A%2F%2Ftracker.leechers-paradise.org%3A6969&amp;tr=udp%3A%2F%2Fzer0day.ch%3A1337&amp;tr=udp%3A%2F%2Fopen.demonii.com%3A1337&amp;tr=udp%3A%2F%2Ftracker.coppersurfer.tk%3A6969&amp;tr=udp%3A%2F%2Fexodus.desync.com%3A6969","seeders":0,"leechers":2,"uploader":"demonoidt","files":6,"time":1463943270,"description":"Samples\r\n \nhttp://adultwallpapers.co.in/busty-haruka-ohsawa-rides-cock/\r\n \nhttp://demonoid.co/2016/05/22/busty-haruka-ohsawa-rides-cock/","torrent":{"xt":"urn:btih:fe33855facda2dc1005cd4dc10291ee697ad51d5","amp;dn":"Busty+Haruka+Ohsawa+rides+cock","amp;tr":["udp%3A%2F%2Ftracker.leechers-paradise.org%3A6969","udp%3A%2F%2Fzer0day.ch%3A1337","udp%3A%2F%2Fopen.demonii.com%3A1337","udp%3A%2F%2Ftracker.coppersurfer.tk%3A6969","udp%3A%2F%2Fexodus.desync.com%3A6969"],"infoHash":"fe33855facda2dc1005cd4dc10291ee697ad51d5","infoHashBuffer":{"type":"Buffer","data":[254,51,133,95,172,218,45,193,0,92,212,220,16,41,30,230,151,173,81,213]},"announce":[],"urlList":[]}}